galaxyutils/__init__.py
galaxyutils/config_parser.py
galaxyutils/time_tracker.py
galaxyutils-0.1.5.dist-info/LICENSE
galaxyutils-0.1.5.dist-info/METADATA
galaxyutils-0.1.5.dist-info/WHEEL
galaxyutils-0.1.5.dist-info/top_level.txt
galaxyutils-0.1.5.dist-info/RECORD
