Metadata-Version: 2.1
Name: galaxyutils
Version: 0.1.5
Summary: This module contains utilities that Galaxy 2.0 plugin developers may find useful.
Home-page: https://github.com/tylerbrawl/Galaxy-Utils
Author: Tyler Nichols
Author-email: tylerbrawl@gmail.com
License: UNKNOWN
Platform: UNKNOWN
Classifier: License :: OSI Approved :: MIT License
Classifier: Natural Language :: English
Classifier: Operating System :: OS Independent
Classifier: Programming Language :: Python :: 3
Classifier: Topic :: Utilities
Requires-Python: >=3.7
